mini_six/__init__.py
mini_six/core/__init__.py
mini_six/core/abstract.py
mini_six/core/config.py
mini_six/core/interface.py
mini_six/logger.py
mini_six/plugin.py
mini_six/portable/__init__.py
mini_six/portable/win32/__init__.py
mini_six/portable/win32/observer.py
mini_six/portable/win32/operation/__init__.py
mini_six/portable/win32/operation/key_map.py
mini_six/portable/win32/operation/keyboard.py
mini_six/portable/win32/operation/mouse.py
mini_six/portable/win32/windll.py
mini_six-0.1.10.dist-info/LICENSE
mini_six-0.1.10.dist-info/WHEEL
mini_six-0.1.10.dist-info/METADATA
mini_six-0.1.10.dist-info/RECORD
