Metadata-Version: 2.1
Name: mini-six
Version: 0.1.10
Summary: A cross-platform, highly scalable, maintainable, machine-aware, machine-aware, limited state machine framework.
Home-page: https://github.com/Six-Project/six.git
License: MIT
Author: TsangHans
Author-email: gzzenghan@189.cn
Requires-Python: >=3.7,<4.0
Classifier: License :: OSI Approved :: MIT License
Classifier: Programming Language :: Python :: 3
Classifier: Programming Language :: Python :: 3.7
Classifier: Programming Language :: Python :: 3.8
Classifier: Programming Language :: Python :: 3.9
Classifier: Programming Language :: Python :: 3.10
Classifier: Programming Language :: Python :: 3.11
Requires-Dist: numpy (==1.21.6)
Requires-Dist: opencv-python (==4.4.0.46)
Project-URL: Repository, https://github.com/Six-Project/six.git
